kqml/__init__.py
kqml/cl_json.py
kqml/kqml_dispatcher.py
kqml/kqml_exceptions.py
kqml/kqml_list.py
kqml/kqml_module.py
kqml/kqml_performative.py
kqml/kqml_quotation.py
kqml/kqml_reader.py
kqml/kqml_string.py
kqml/kqml_token.py
kqml/util.py
pykqml-1.3.dist-info/LICENSE
pykqml-1.3.dist-info/METADATA
pykqml-1.3.dist-info/WHEEL
pykqml-1.3.dist-info/top_level.txt
pykqml-1.3.dist-info/RECORD
