Metadata-Version: 2.1
Name: pykqml
Version: 1.3
Summary: KQML messaging classes in Python.
Home-page: http://github.com/bgyori/pykqml
Author: Benjamin M. Gyori
Author-email: benjamin_gyori@hms.harvard.edu
License: UNKNOWN
Keywords: kqml,agent,nlp,communication,dialogue
Platform: UNKNOWN
Classifier: Development Status :: 4 - Beta
Classifier: Environment :: Console
Classifier: Intended Audience :: Science/Research
Classifier: License :: OSI Approved :: BSD License
Classifier: Operating System :: OS Independent
Classifier: Programming Language :: Python :: 3
